cloudflarify/__init__.py
cloudflarify/tunnel.py
cloudflarify-1.0.0.dist-info/METADATA
cloudflarify-1.0.0.dist-info/WHEEL
cloudflarify-1.0.0.dist-info/top_level.txt
cloudflarify-1.0.0.dist-info/RECORD
