Metadata-Version: 2.4
Name: cloudflarify
Version: 1.0.0
Summary: A Python wrapper to run Cloudflare tunnels programmatically
Home-page: https://github.com/Jobians/cloudflarify
Author: JOBIANS TECHIE
Author-email: jobianstechie@gmail.com
Classifier: Programming Language :: Python :: 3
Classifier: License :: OSI Approved :: MIT License
Classifier: Operating System :: OS Independent
Requires-Python: >=3.7
Requires-Dist: aiohttp
Requires-Dist: tqdm
Dynamic: author
Dynamic: author-email
Dynamic: classifier
Dynamic: description
Dynamic: description-content-type
Dynamic: home-page
Dynamic: requires-dist
Dynamic: requires-python
Dynamic: summary
